ray_on_golem/__init__.py
ray_on_golem/__main__.py
ray_on_golem/cli.py
ray_on_golem/client/__init__.py
ray_on_golem/client/client.py
ray_on_golem/client/exceptions.py
ray_on_golem/ctl/__init__.py
ray_on_golem/ctl/ctl.py
ray_on_golem/ctl/log.py
ray_on_golem/exceptions.py
ray_on_golem/log.py
ray_on_golem/main.py
ray_on_golem/network_stats/__init__.py
ray_on_golem/network_stats/main.py
ray_on_golem/network_stats/services/__init__.py
ray_on_golem/network_stats/services/network_stats.py
ray_on_golem/provider/__init__.py
ray_on_golem/provider/exceptions.py
ray_on_golem/provider/log.py
ray_on_golem/provider/node_provider.py
ray_on_golem/provider/ssh_command_runner.py
ray_on_golem/reputation/__init__.py
ray_on_golem/reputation/admin.py
ray_on_golem/reputation/cli.py
ray_on_golem/reputation/migrations/models/0_20240311095546_init.py
ray_on_golem/reputation/migrations/models/2_20240312164006_update.py
ray_on_golem/reputation/migrations/models/3_20240314085535_blacklisted_until_index.py
ray_on_golem/reputation/models.py
ray_on_golem/reputation/plugins/__init__.py
ray_on_golem/reputation/plugins/blacklist.py
ray_on_golem/reputation/plugins/score.py
ray_on_golem/reputation/service.py
ray_on_golem/reputation/updater.py
ray_on_golem/server/__init__.py
ray_on_golem/server/cluster/__init__.py
ray_on_golem/server/cluster/cluster.py
ray_on_golem/server/cluster/nodes.py
ray_on_golem/server/cluster/sidecars.py
ray_on_golem/server/exceptions.py
ray_on_golem/server/main.py
ray_on_golem/server/middlewares.py
ray_on_golem/server/mixins.py
ray_on_golem/server/models.py
ray_on_golem/server/services/__init__.py
ray_on_golem/server/services/golem/__init__.py
ray_on_golem/server/services/golem/golem.py
ray_on_golem/server/services/golem/helpers/__init__.py
ray_on_golem/server/services/golem/helpers/demand_config.py
ray_on_golem/server/services/golem/helpers/manager_stack.py
ray_on_golem/server/services/golem/manager_stack.py
ray_on_golem/server/services/golem/manifest.py
ray_on_golem-0.13.0.dist-info/LICENSE
ray_on_golem-0.13.0.dist-info/METADATA
ray_on_golem-0.13.0.dist-info/WHEEL
ray_on_golem-0.13.0.dist-info/entry_points.txt
ray_on_golem-0.13.0.dist-info/RECORD
