Metadata-Version: 2.1
Name: ray-on-golem
Version: 0.13.0
Summary: Golem Network integration with Ray
Author: Golem Factory
Author-email: contact@golem.network
Requires-Python: >=3.8.1,<4.0.0
Classifier: Programming Language :: Python :: 3
Classifier: Programming Language :: Python :: 3.9
Classifier: Programming Language :: Python :: 3.10
Classifier: Programming Language :: Python :: 3.11
Classifier: Programming Language :: Python :: 3.12
Requires-Dist: aerich (>=0.7.2,<0.8.0)
Requires-Dist: aiohttp (>=3,<4)
Requires-Dist: appdirs (>=1.4.4,<2.0.0)
Requires-Dist: click (>=8,<9)
Requires-Dist: dpath (>=2.1.6,<3.0.0)
Requires-Dist: golem-core (>=0.7.5,<0.8.0)
Requires-Dist: golem-node (>=0.16.0,<0.17.0)
Requires-Dist: prettytable (>=3.10.0,<4.0.0)
Requires-Dist: psutil (>=5.9.8,<6.0.0)
Requires-Dist: pydantic (<2)
Requires-Dist: ray[default] (>=2.9.3,<2.10.0)
Requires-Dist: requests (>=2,<3)
Requires-Dist: setuptools (>=69.5.1,<70.0.0)
Requires-Dist: toml (>=0.10.2,<0.11.0)
Requires-Dist: tortoise-orm (>=0.20.0,<0.21.0)
Requires-Dist: websocat (>=1.13.0,<2.0.0)
Requires-Dist: yarl (>=1.9.4,<2.0.0)
